autoimportutf8-0.0.2.dist-info/METADATA
autoimportutf8-0.0.2.dist-info/WHEEL
autoimportutf8-0.0.2.dist-info/entry_points.txt
autoimportutf8-0.0.2.dist-info/licenses/LICENSE
autoimportutf8/__init__.py
autoimportutf8/__main__.py
autoimportutf8/entrypoints/__init__.py
autoimportutf8/entrypoints/cli.py
autoimportutf8/model.py
autoimportutf8/py.typed
autoimportutf8/services.py
autoimportutf8/version.py
autoimportutf8-0.0.2.dist-info/RECORD
